Metadata-Version: 1.0
Name: distributions-masm
Version: 0.1
Summary: Gaussian distributions
Home-page: UNKNOWN
Author: Miguel Soriano
Author-email: msorianomontero@gmail.com
License: UNKNOWN
Platform: UNKNOWN
